pymace/__init__.py
pymace/aero/__init__.py
pymace/aero/datatypes.py
pymace/aero/generalfunctions.py
pymace/aero/flightconditions/__init__.py
pymace/aero/flightconditions/climb.py
pymace/aero/flightconditions/climb_scipy.py
pymace/aero/flightconditions/efficiency_flight.py
pymace/aero/flightconditions/efficiency_flight_low_fid.py
pymace/aero/flightconditions/glidingflight.py
pymace/aero/flightconditions/glidingflight_jf.py
pymace/aero/flightconditions/horizontalflight.py
pymace/aero/flightconditions/landing.py
pymace/aero/flightconditions/takeoff.py
pymace/aero/flightconditions/takeoff_jf.py
pymace/aero/flightconditions/turningflight.py
pymace/aero/implementations/__init__.py
pymace/aero/implementations/aero.py
pymace/aero/implementations/airfoil_analyses.py
pymace/aero/implementations/runsubprocess.py
pymace/aero/implementations/viscous_drag.py
pymace/aero/implementations/viscousdrag.py
pymace/aero/implementations/avl/__init__.py
pymace/aero/implementations/avl/athenavortexlattice.py
pymace/aero/implementations/avl/geometry_and_mass_files.py
pymace/aero/implementations/avl/geometry_and_mass_files_v2.py
pymace/aero/implementations/xfoil/__init__.py
pymace/aero/implementations/xfoil/xfoilpolars.py
pymace/cli/__init__.py
pymace/cli/tools.py
pymace/domain/__init__.py
pymace/domain/battery.py
pymace/domain/cache.py
pymace/domain/fuselage.py
pymace/domain/general_functions.py
pymace/domain/landing_gear.py
pymace/domain/params.py
pymace/domain/parser.py
pymace/domain/plane.py
pymace/domain/propeller.py
pymace/domain/propulsor.py
pymace/domain/results.py
pymace/domain/testplane.py
pymace/domain/vehicle.py
pymace/domain/wing.py
pymace/new/__init__.py
pymace/new/aero.py
pymace/new/analysis.py
pymace/new/domain.py
pymace/new/geometries.py
pymace/new/properties.py
pymace/new/structure.py
pymace/setup/__init__.py
pymace/setup/airfoils.py
pymace/setup/mace_setup.py
pymace/test/__init__.py
pymace/test/perftest.py
pymace/test/size.py
pymace/test/vehicle_setup.py
pymace-0.0.3.dist-info/METADATA
pymace-0.0.3.dist-info/WHEEL
pymace-0.0.3.dist-info/entry_points.txt
pymace-0.0.3.dist-info/licenses/LICENSE.txt
pymace-0.0.3.dist-info/RECORD
