Metadata-Version: 2.4
Name: pymace
Version: 0.0.3
Summary: A package for evaluating and analysing modell Aircraft
Project-URL: Repository, https://github.com/TheHenrik/mace
Project-URL: Documentation, https://pymace.readthedocs.io/en/latest/
Author-email: Tjalf Stadel <tjalf13+mace@gmail.com>, Jannik Frank <jannik.frank@akamodell.de>
License:  GNU GENERAL PUBLIC LICENSE
License-File: LICENSE.txt
Keywords: Akamodell Stuttgart,aircraft,modell aircraft
Classifier: Development Status :: 3 - Alpha
Classifier: Operating System :: OS Independent
Classifier: Programming Language :: Python :: 3
Requires-Python: >=3.11
Requires-Dist: bs4
Requires-Dist: matplotlib
Requires-Dist: numpy
Requires-Dist: psutil
Requires-Dist: requests
Requires-Dist: scikit-optimize
Requires-Dist: scipy
Requires-Dist: tabulate
Requires-Dist: tqdm
Provides-Extra: dev
Requires-Dist: ruff>=0.6.4; extra == 'dev'
Provides-Extra: docs
Requires-Dist: mkdocs-material>=9.5.42; extra == 'docs'
Requires-Dist: mkdocs>=1.6.1; extra == 'docs'
Requires-Dist: mkdocstrings[python]>=0.26.2; extra == 'docs'
Provides-Extra: test
Requires-Dist: pytest; extra == 'test'
